Metadata-Version: 1.1
Name: jumpdatabase
Version: 0.1
Summary: minimal json local database
Home-page: https://gitlab.com/opensource-university/jumpdb
Author: lagvidilo
Author-email: informabox.contact@gmail.com
License: lgpl-3.0
Keywords: DATABASE,JSON,LOCAL,MICRO
Platform: UNKNOWN
Classifier: Development Status :: 3 - Alpha
Classifier: Intended Audience :: Developers
Classifier: Topic :: Software Development :: Build Tools
Classifier: Programming Language :: Python :: 3
Classifier: Programming Language :: Python :: 3.6
Classifier: Programming Language :: Python :: 3.7
Classifier: Programming Language :: Python :: 3.8
